aiodistributor/__init__.py
aiodistributor/distibuted_semaphore.py
aiodistributor/distributed_barrier.py
aiodistributor/distributed_bounded_semaphore.py
aiodistributor/distributed_cache.py
aiodistributor/distributed_condition.py
aiodistributor/distributed_event.py
aiodistributor/distributed_lock.py
aiodistributor/distributed_notifier.py
aiodistributor/distributed_sliding_counter.py
aiodistributor/distributed_task.py
aiodistributor/distributed_waiter.py
aiodistributor/py.typed
aiodistributor/common/__init__.py
aiodistributor/common/loggers.py
aiodistributor-0.0.3.3.dist-info/LICENSE
aiodistributor-0.0.3.3.dist-info/METADATA
aiodistributor-0.0.3.3.dist-info/WHEEL
aiodistributor-0.0.3.3.dist-info/top_level.txt
aiodistributor-0.0.3.3.dist-info/RECORD
