Metadata-Version: 2.1
Name: aiodistributor
Version: 0.0.3.3
Summary: Python asynchronous library for synchronizing replicated microservices
Home-page: https://github.com/malik89303/aiodistributor
License: Apache License 2.0
Platform: POSIX
Classifier: License :: OSI Approved :: Apache Software License
Classifier: Development Status :: 2 - Pre-Alpha
Classifier: Programming Language :: Python
Classifier: Programming Language :: Python :: 3.10
Classifier: Programming Language :: Python :: 3.11
Classifier: Programming Language :: Python :: 3 :: Only
Classifier: Operating System :: POSIX
Classifier: Environment :: Web Environment
Classifier: Intended Audience :: Developers
Classifier: Topic :: Software Development
Classifier: Topic :: Software Development :: Libraries
Classifier: Framework :: AsyncIO
Requires-Python: >=3.10
License-File: LICENSE
Requires-Dist: redis
Requires-Dist: ujson
